pipeGEM/__init__.py
pipeGEM/_constant.py
pipeGEM/analysis/__init__.py
pipeGEM/analysis/_consistency.py
pipeGEM/analysis/_dim_reduction.py
pipeGEM/analysis/_flux.py
pipeGEM/analysis/_gapsplit.py
pipeGEM/analysis/_ko.py
pipeGEM/analysis/_mapping.py
pipeGEM/analysis/_problem.py
pipeGEM/analysis/_reducing.py
pipeGEM/analysis/_stat.py
pipeGEM/analysis/_threshold.py
pipeGEM/analysis/_utils.py
pipeGEM/analysis/graph/__init__.py
pipeGEM/analysis/graph/_transform.py
pipeGEM/analysis/lp/_FASTCORE.py
pipeGEM/analysis/lp/_SWIFTCORE.py
pipeGEM/analysis/lp/__init__.py
pipeGEM/analysis/pathway/__init__.py
pipeGEM/analysis/pathway/_base.py
pipeGEM/analysis/results/__init__.py
pipeGEM/analysis/results/_base.py
pipeGEM/analysis/results/_file_manager.py
pipeGEM/analysis/results/consistency.py
pipeGEM/analysis/results/corr.py
pipeGEM/analysis/results/data.py
pipeGEM/analysis/results/dim_reduction.py
pipeGEM/analysis/results/flux_analysis.py
pipeGEM/analysis/results/group_comp.py
pipeGEM/analysis/results/integration.py
pipeGEM/analysis/results/ko_analysis.py
pipeGEM/analysis/results/scaling.py
pipeGEM/analysis/results/stat.py
pipeGEM/analysis/results/task.py
pipeGEM/analysis/results/thresholds.py
pipeGEM/analysis/scaling/__init__.py
pipeGEM/analysis/scaling/_base.py
pipeGEM/analysis/scaling/_scalers.py
pipeGEM/analysis/tasks/__init__.py
pipeGEM/analysis/tasks/_base.py
pipeGEM/analysis/tasks/_var.py
pipeGEM/analysis/tasks/gapfill.py
pipeGEM/analysis/tasks/task_files/tasks_for_imm1415.json
pipeGEM/analysis/tasks/task_files/tasks_human1.json
pipeGEM/analysis/tasks/task_files/tasks_recon3d.json
pipeGEM/cli/__init__.py
pipeGEM/cli/__main__.py
pipeGEM/cli/_doc.py
pipeGEM/cli/_io.py
pipeGEM/cli/_utils.py
pipeGEM/cli/cli.py
pipeGEM/cli/configs/comparison.toml
pipeGEM/cli/configs/gene_data.toml
pipeGEM/cli/configs/mapping.toml
pipeGEM/cli/configs/model.toml
pipeGEM/cli/configs/multi_model.toml
pipeGEM/cli/configs/flux_analysis/pFBA.toml
pipeGEM/cli/configs/gene_data_integration/CORDA.toml
pipegem-0.1.1.dist-info/licenses/LICENSE
pipegem-0.1.1.dist-info/METADATA
pipegem-0.1.1.dist-info/WHEEL
pipegem-0.1.1.dist-info/entry_points.txt
pipegem-0.1.1.dist-info/top_level.txt
pipegem-0.1.1.dist-info/RECORD
