Metadata-Version: 2.4
Name: pipeGEM
Version: 0.1.1
Summary: Processing and integrating data with genome-scale metabolic models (GEM)
Author-email: Yu-Te Lin <qwerty239qwe@gmail.com>
Project-URL: Homepage, https://github.com/qwerty239qwe/pipeGEM
Keywords: metabolism,metabolic-model,computational-biology,system-biology,cobra
Classifier: License :: OSI Approved :: GNU General Public License v3 (GPLv3)
Classifier: Programming Language :: Python
Classifier: Programming Language :: Python :: 3.8
Classifier: Programming Language :: Python :: 3.9
Classifier: Programming Language :: Python :: 3.10
Classifier: Programming Language :: Python :: 3.11
Classifier: Programming Language :: Python :: 3.12
Requires-Python: >=3.8
License-File: LICENSE
Requires-Dist: cobra
Requires-Dist: pandas
Requires-Dist: numpy
Requires-Dist: scipy
Requires-Dist: matplotlib
Requires-Dist: requests
Requires-Dist: scikit-learn
Requires-Dist: scikit-posthocs
Requires-Dist: seaborn
Requires-Dist: umap-learn
Requires-Dist: biodbs
Requires-Dist: tqdm
Requires-Dist: optlang
Requires-Dist: networkx
Requires-Dist: zeep
Requires-Dist: pint
Requires-Dist: pingouin
Requires-Dist: scanpy
Requires-Dist: tomlkit
Requires-Dist: dask[distributed]
Requires-Dist: openpyxl
Provides-Extra: dev
Requires-Dist: pip-tools; extra == "dev"
Requires-Dist: pytest; extra == "dev"
Requires-Dist: flake8; extra == "dev"
Provides-Extra: doc
Requires-Dist: numpydoc; extra == "doc"
Requires-Dist: nbconvert; extra == "doc"
Requires-Dist: ipykernel; extra == "doc"
Requires-Dist: sphinx; extra == "doc"
Requires-Dist: sphinx-copybutton; extra == "doc"
Requires-Dist: sphinx-issues; extra == "doc"
Requires-Dist: sphinx-design; extra == "doc"
Requires-Dist: pydata_sphinx_theme; extra == "doc"
Requires-Dist: myst-nb; extra == "doc"
Requires-Dist: ipywidgets; extra == "doc"
Provides-Extra: dlkcat
Requires-Dist: torch; extra == "dlkcat"
Requires-Dist: rdkit; extra == "dlkcat"
Dynamic: license-file
